{"1": {"neighbours": [90], "node_range": 13.5, "x": 5.066344, "y": 5.915518}, "2": {"neighbours": [43, 53, 120], "node_range": 13.5, "x": 10.403292, "y": 126.482611}, "3": {"neighbours": [15, 61, 71, 111, 139], "node_range": 13.5, "x": 24.067184, "y": 142.454588}, "4": {"neighbours": [30, 58, 117, 136], "node_range": 13.5, "x": 122.960996, "y": 131.512196}, "5": {"neighbours": [56, 78], "node_range": 13.5, "x": 47.099039, "y": 3.028387}, "6": {"neighbours": [13, 72, 112, 125, 138], "node_range": 13.5, "x": 131.853931, "y": 15.694076}, "7": {"neighbours": [35, 59], "node_range": 13.5, "x": 98.55744, "y": 127.2987}, "8": {"neighbours": [11, 66, 67, 130, 143], "node_range": 13.5, "x": 121.501673, "y": 86.574465}, "9": {"neighbours": [52, 85, 132], "node_range": 13.5, "x": 91.873512, "y": 62.367809}, "10": {"neighbours": [33, 83], "node_range": 13.5, "x": 128.901601, "y": 48.34952}, "11": {"neighbours": [8, 66, 75, 103, 143], "node_range": 13.5, "x": 111.404771, "y": 84.548477}, "12": {"neighbours": [21, 24, 115], "node_range": 13.5, "x": 103.839997, "y": 31.469513}, "13": {"neighbours": [6, 106, 112, 138], "node_range": 13.5, "x": 132.750911, "y": 24.588987}, "14": {"neighbours": [129], "node_range": 13.5, "x": 146.974931, "y": 61.60435}, "15": {"neighbours": [3, 61], "node_range": 13.5, "x": 33.882871, "y": 136.721875}, "16": {"neighbours": [31, 137], "node_range": 13.5, "x": 8.923094, "y": 97.829723}, "17": {"neighbours": [19, 36, 99, 100], "node_range": 13.5, "x": 72.901124, "y": 71.915775}, "18": {"neighbours": [60, 70, 92], "node_range": 13.5, "x": 94.922865, "y": 106.465391}, "19": {"neighbours": [17, 36, 99, 100], "node_range": 13.5, "x": 73.852987, "y": 72.756434}, "20": {"neighbours": [26, 74, 134], "node_range": 13.5, "x": 49.254805, "y": 69.879676}, "21": {"neighbours": [12, 22, 24, 115], "node_range": 13.5, "x": 102.165333, "y": 24.630861}, "22": {"neighbours": [21, 24, 115], "node_range": 13.5, "x": 103.34053, "y": 17.705774}, "23": {"neighbours": [79], "node_range": 13.5, "x": 67.266325, "y": 33.594062}, "24": {"neighbours": [12, 21, 22, 115], "node_range": 13.5, "x": 108.320036, "y": 27.156149}, "25": {"neighbours": [76, 88, 128], "node_range": 13.5, "x": 4.910143, "y": 53.237184}, "26": {"neighbours": [20, 74, 134], "node_range": 13.5, "x": 50.401235, "y": 68.082467}, "27": {"neighbours": [32, 44, 48, 55, 101, 149], "node_range": 13.5, "x": 71.920211, "y": 131.29362}, "28": {"neighbours": [105, 140, 144], "node_range": 13.5, "x": 18.579934, "y": 78.355705}, "29": {"neighbours": [34, 39, 86, 98], "node_range": 13.5, "x": 66.282274, "y": 49.205989}, "30": {"neighbours": [4, 117, 136], "node_range": 13.5, "x": 125.083907, "y": 132.747802}, "31": {"neighbours": [16, 140], "node_range": 13.5, "x": 14.24736, "y": 92.25663}, "32": {"neighbours": [27, 48, 101, 108, 149], "node_range": 13.5, "x": 66.296261, "y": 138.320896}, "33": {"neighbours": [10], "node_range": 13.5, "x": 116.02043, "y": 45.689842}, "34": {"neighbours": [29, 39, 98], "node_range": 13.5, "x": 61.782927, "y": 48.802933}, "35": {"neighbours": [7, 58, 117, 148], "node_range": 13.5, "x": 108.608562, "y": 126.333288}, "36": {"neighbours": [17, 19], "node_range": 13.5, "x": 71.255785, "y": 80.146015}, "37": {"neighbours": [67, 131, 136], "node_range": 13.5, "x": 121.559035, "y": 110.65658}, "38": {"neighbours": [49, 87, 127], "node_range": 13.5, "x": 28.396757, "y": 89.389423}, "39": {"neighbours": [29, 34, 99, 100], "node_range": 13.5, "x": 64.733596, "y": 60.877148}, "40": {"neighbours": [53, 65, 68, 89, 107, 150], "node_range": 13.5, "x": 21.354389, "y": 114.907718}, "41": {"neighbours": [54, 90], "node_range": 13.5, "x": 15.147173, "y": 16.260558}, "42": {"neighbours": [56, 78, 97], "node_range": 13.5, "x": 60.042606, "y": 7.364855}, "43": {"neighbours": [2, 120], "node_range": 13.5, "x": 2.055388, "y": 134.197359}, "44": {"neighbours": [27, 48, 55, 104, 123, 124, 149], "node_range": 13.5, "x": 73.347596, "y": 121.459578}, "45": {"neighbours": [50, 133], "node_range": 13.5, "x": 52.451427, "y": 138.699568}, "46": {"neighbours": [141], "node_range": 13.5, "x": 88.124926, "y": 37.218823}, "47": {"neighbours": [57, 63, 91, 122, 145, 147], "node_range": 13.5, "x": 27.793442, "y": 40.819992}, "48": {"neighbours": [27, 32, 44, 55, 101, 149], "node_range": 13.5, "x": 66.610974, "y": 130.231222}, "49": {"neighbours": [38, 87, 127], "node_range": 13.5, "x": 32.516389, "y": 89.611373}, "50": {"neighbours": [45, 94], "node_range": 13.5, "x": 45.645714, "y": 129.155673}, "51": {"neighbours": [79, 135], "node_range": 13.5, "x": 52.26782, "y": 21.666615}, "52": {"neighbours": [9, 85, 109], "node_range": 13.5, "x": 93.100678, "y": 65.76413}, "53": {"neighbours": [2, 40, 68], "node_range": 13.5, "x": 17.097995, "y": 125.122152}, "54": {"neighbours": [41, 63, 126, 128, 145], "node_range": 13.5, "x": 14.173494, "y": 28.786244}, "55": {"neighbours": [27, 44, 48, 101, 123, 124, 149], "node_range": 13.5, "x": 64.624999, "y": 123.225561}, "56": {"neighbours": [5, 42, 78], "node_range": 13.5, "x": 51.480577, "y": 2.082833}, "57": {"neighbours": [47, 91, 122], "node_range": 13.5, "x": 34.278914, "y": 52.149083}, "58": {"neighbours": [4, 35, 117, 136, 148], "node_range": 13.5, "x": 112.472765, "y": 126.16403}, "59": {"neighbours": [7, 110], "node_range": 13.5, "x": 91.149759, "y": 138.382229}, "60": {"neighbours": [18, 70, 92], "node_range": 13.5, "x": 92.905186, "y": 105.273064}, "61": {"neighbours": [3, 15, 71, 111, 139], "node_range": 13.5, "x": 24.016388, "y": 138.545179}, "62": {"neighbours": [80], "node_range": 13.5, "x": 79.353174, "y": 8.356702}, "63": {"neighbours": [47, 54, 126, 145], "node_range": 13.5, "x": 25.226868, "y": 31.005591}, "64": {"neighbours": [73], "node_range": 13.5, "x": 147.229275, "y": 123.212816}, "65": {"neighbours": [40, 68, 89, 107, 150], "node_range": 13.5, "x": 30.100437, "y": 116.720471}, "66": {"neighbours": [8, 11, 67, 75, 103, 130, 131, 143], "node_range": 13.5, "x": 118.733312, "y": 88.90952}, "67": {"neighbours": [8, 37, 66, 69, 114, 130, 131, 142, 143], "node_range": 13.5, "x": 127.541404, "y": 98.569917}, "68": {"neighbours": [40, 53, 65, 89, 150], "node_range": 13.5, "x": 23.993988, "y": 124.04639}, "69": {"neighbours": [67, 102, 114, 142], "node_range": 13.5, "x": 137.33382, "y": 103.322306}, "70": {"neighbours": [18, 60, 92], "node_range": 13.5, "x": 94.987534, "y": 99.569415}, "71": {"neighbours": [3, 61, 111, 139], "node_range": 13.5, "x": 18.567647, "y": 145.68732}, "72": {"neighbours": [6, 125], "node_range": 13.5, "x": 132.645501, "y": 4.707727}, "73": {"neighbours": [64], "node_range": 13.5, "x": 142.09647, "y": 133.769424}, "74": {"neighbours": [20, 26, 134], "node_range": 13.5, "x": 45.684782, "y": 61.529189}, "75": {"neighbours": [11, 66, 92, 103], "node_range": 13.5, "x": 105.78826, "y": 91.003166}, "76": {"neighbours": [25, 128], "node_range": 13.5, "x": 0.194829, "y": 48.630129}, "77": {"neighbours": [116, 121], "node_range": 13.5, "x": 51.948584, "y": 105.111363}, "78": {"neighbours": [5, 42, 56], "node_range": 13.5, "x": 51.321062, "y": 1.894659}, "79": {"neighbours": [23, 51], "node_range": 13.5, "x": 58.930909, "y": 26.933775}, "80": {"neighbours": [62], "node_range": 13.5, "x": 80.487736, "y": 0.217394}, "81": {"neighbours": [88, 144, 147], "node_range": 13.5, "x": 15.836527, "y": 62.503882}, "82": {"neighbours": [83, 84], "node_range": 13.5, "x": 149.933591, "y": 43.314869}, "83": {"neighbours": [10, 82], "node_range": 13.5, "x": 138.430135, "y": 48.57465}, "84": {"neighbours": [82, 112, 138], "node_range": 13.5, "x": 144.378379, "y": 31.856291}, "85": {"neighbours": [9, 52, 132, 141], "node_range": 13.5, "x": 92.414137, "y": 53.062067}, "86": {"neighbours": [29, 132, 141], "node_range": 13.5, "x": 78.530287, "y": 48.074259}, "87": {"neighbours": [38, 49], "node_range": 13.5, "x": 32.474387, "y": 85.436988}, "88": {"neighbours": [25, 81, 144, 147], "node_range": 13.5, "x": 15.8192, "y": 58.992388}, "89": {"neighbours": [40, 65, 68, 107, 150], "node_range": 13.5, "x": 32.23803, "y": 113.362439}, "90": {"neighbours": [1, 41], "node_range": 13.5, "x": 8.360753, "y": 10.326404}, "91": {"neighbours": [47, 57, 122, 147], "node_range": 13.5, "x": 31.33931, "y": 47.058645}, "92": {"neighbours": [18, 60, 70, 75, 103], "node_range": 13.5, "x": 101.580997, "y": 99.084809}, "93": {"neighbours": [109], "node_range": 13.5, "x": 110.959991, "y": 69.924449}, "94": {"neighbours": [50], "node_range": 13.5, "x": 48.772622, "y": 120.945584}, "95": {"neighbours": [135], "node_range": 13.5, "x": 38.03134, "y": 25.112345}, "96": {"neighbours": [119, 137], "node_range": 13.5, "x": 3.180262, "y": 111.365202}, "97": {"neighbours": [42], "node_range": 13.5, "x": 65.881755, "y": 0.871051}, "98": {"neighbours": [29, 34], "node_range": 13.5, "x": 62.600293, "y": 46.550408}, "99": {"neighbours": [17, 19, 39, 100], "node_range": 13.5, "x": 65.21536, "y": 63.868358}, "100": {"neighbours": [17, 19, 39, 99], "node_range": 13.5, "x": 67.404205, "y": 62.909884}, "101": {"neighbours": [27, 32, 48, 55, 108, 149], "node_range": 13.5, "x": 67.630596, "y": 133.936733}, "102": {"neighbours": [69, 114, 142], "node_range": 13.5, "x": 145.994251, "y": 104.999613}, "103": {"neighbours": [11, 66, 75, 92], "node_range": 13.5, "x": 107.452976, "y": 89.395068}, "104": {"neighbours": [44, 113, 123, 124], "node_range": 13.5, "x": 74.139426, "y": 110.490828}, "105": {"neighbours": [28, 140, 144], "node_range": 13.5, "x": 11.840154, "y": 77.820525}, "106": {"neighbours": [13, 112], "node_range": 13.5, "x": 124.733196, "y": 32.285818}, "107": {"neighbours": [40, 65, 89, 116, 127, 150], "node_range": 13.5, "x": 32.117617, "y": 109.847917}, "108": {"neighbours": [32, 101], "node_range": 13.5, "x": 65.044222, "y": 144.022489}, "109": {"neighbours": [52, 93], "node_range": 13.5, "x": 105.645397, "y": 66.377861}, "110": {"neighbours": [59], "node_range": 13.5, "x": 89.802557, "y": 141.266352}, "111": {"neighbours": [3, 61, 71, 139], "node_range": 13.5, "x": 21.622655, "y": 149.363014}, "112": {"neighbours": [6, 13, 84, 106, 138], "node_range": 13.5, "x": 135.134409, "y": 25.138856}, "113": {"neighbours": [104, 118], "node_range": 13.5, "x": 78.632994, "y": 101.667604}, "114": {"neighbours": [67, 69, 102, 142], "node_range": 13.5, "x": 137.870188, "y": 100.877866}, "115": {"neighbours": [12, 21, 22, 24], "node_range": 13.5, "x": 110.407768, "y": 26.304843}, "116": {"neighbours": [77, 107, 121], "node_range": 13.5, "x": 42.506786, "y": 104.474189}, "117": {"neighbours": [4, 30, 35, 58, 136, 148], "node_range": 13.5, "x": 119.685316, "y": 129.192577}, "118": {"neighbours": [113], "node_range": 13.5, "x": 80.52992, "y": 94.652316}, "119": {"neighbours": [96, 137], "node_range": 13.5, "x": 1.646992, "y": 114.697473}, "120": {"neighbours": [2, 43], "node_range": 13.5, "x": 2.431041, "y": 134.967161}, "121": {"neighbours": [77, 116], "node_range": 13.5, "x": 51.239995, "y": 100.72184}, "122": {"neighbours": [47, 57, 91], "node_range": 13.5, "x": 36.90899, "y": 50.509841}, "123": {"neighbours": [44, 55, 104, 124, 149], "node_range": 13.5, "x": 66.981372, "y": 115.24866}, "124": {"neighbours": [44, 55, 104, 123, 149], "node_range": 13.5, "x": 74.284304, "y": 117.0009}, "125": {"neighbours": [6, 72], "node_range": 13.5, "x": 132.483106, "y": 5.420715}, "126": {"neighbours": [54, 63, 128, 145], "node_range": 13.5, "x": 13.576268, "y": 37.004473}, "127": {"neighbours": [38, 49, 107], "node_range": 13.5, "x": 26.348979, "y": 98.716428}, "128": {"neighbours": [25, 54, 76, 126, 145], "node_range": 13.5, "x": 10.052926, "y": 40.916167}, "129": {"neighbours": [14], "node_range": 13.5, "x": 138.458236, "y": 64.391859}, "130": {"neighbours": [8, 66, 67, 131, 143], "node_range": 13.5, "x": 120.255703, "y": 95.055127}, "131": {"neighbours": [37, 66, 67, 130, 143], "node_range": 13.5, "x": 117.117685, "y": 100.004381}, "132": {"neighbours": [9, 85, 86, 141], "node_range": 13.5, "x": 87.813362, "y": 53.292991}, "133": {"neighbours": [45], "node_range": 13.5, "x": 47.42639, "y": 143.25471}, "134": {"neighbours": [20, 26, 74], "node_range": 13.5, "x": 45.110932, "y": 63.921112}, "135": {"neighbours": [51, 95], "node_range": 13.5, "x": 42.518244, "y": 22.404288}, "136": {"neighbours": [4, 30, 37, 58, 117], "node_range": 13.5, "x": 123.937582, "y": 121.980607}, "137": {"neighbours": [16, 96, 119], "node_range": 13.5, "x": 7.985695, "y": 110.561956}, "138": {"neighbours": [6, 13, 84, 112], "node_range": 13.5, "x": 135.96094, "y": 24.579346}, "139": {"neighbours": [3, 61, 71, 111], "node_range": 13.5, "x": 17.343823, "y": 146.529262}, "140": {"neighbours": [28, 31, 105], "node_range": 13.5, "x": 15.35093, "y": 83.581404}, "141": {"neighbours": [46, 85, 86, 132], "node_range": 13.5, "x": 87.606702, "y": 49.111044}, "142": {"neighbours": [67, 69, 102, 114], "node_range": 13.5, "x": 137.621561, "y": 106.003771}, "143": {"neighbours": [8, 11, 66, 67, 130, 131], "node_range": 13.5, "x": 121.358155, "y": 93.233943}, "144": {"neighbours": [28, 81, 88, 105], "node_range": 13.5, "x": 14.145928, "y": 69.971064}, "145": {"neighbours": [47, 54, 63, 126, 128], "node_range": 13.5, "x": 21.400161, "y": 34.061256}, "146": {"neighbours": [148], "node_range": 13.5, "x": 105.550191, "y": 147.608843}, "147": {"neighbours": [47, 81, 88, 91], "node_range": 13.5, "x": 19.604445, "y": 51.51596}, "148": {"neighbours": [35, 58, 117, 146], "node_range": 13.5, "x": 111.841754, "y": 139.346158}, "149": {"neighbours": [27, 32, 44, 48, 55, 101, 123, 124], "node_range": 13.5, "x": 65.699193, "y": 127.366398}, "150": {"neighbours": [40, 65, 68, 89, 107], "node_range": 13.5, "x": 25.50463, "y": 112.862878}}