{"1": {"neighbours": [15, 164], "node_range": 16.0, "x": 103.665113, "y": 198.085793}, "2": {"neighbours": [17, 43, 56, 85, 112, 142, 189], "node_range": 16.0, "x": 33.907234, "y": 35.091945}, "3": {"neighbours": [71, 89, 94, 109, 175], "node_range": 16.0, "x": 80.437715, "y": 145.942797}, "4": {"neighbours": [13, 17, 20, 52, 75, 127, 165], "node_range": 16.0, "x": 50.29365, "y": 56.62493}, "5": {"neighbours": [47, 51, 72, 76, 111, 172], "node_range": 16.0, "x": 107.826087, "y": 114.015406}, "6": {"neighbours": [53, 58, 108, 110, 174, 185, 194, 198], "node_range": 16.0, "x": 149.670055, "y": 99.929555}, "7": {"neighbours": [51, 160, 166], "node_range": 16.0, "x": 97.617253, "y": 89.169233}, "8": {"neighbours": [90, 161], "node_range": 16.0, "x": 151.855432, "y": 128.734623}, "9": {"neighbours": [16, 140], "node_range": 16.0, "x": 163.344829, "y": 44.071688}, "10": {"neighbours": [54, 92], "node_range": 16.0, "x": 90.930231, "y": 48.093009}, "11": {"neighbours": [188], "node_range": 16.0, "x": 140.574726, "y": 197.896295}, "12": {"neighbours": [42, 102, 136, 149, 192, 200], "node_range": 16.0, "x": 181.982457, "y": 110.098163}, "13": {"neighbours": [4, 17, 20, 52, 165], "node_range": 16.0, "x": 43.155955, "y": 60.420256}, "14": {"neighbours": [54, 66, 69, 171], "node_range": 16.0, "x": 97.225066, "y": 64.472463}, "15": {"neighbours": [1, 188], "node_range": 16.0, "x": 118.775343, "y": 199.011072}, "16": {"neighbours": [9, 176], "node_range": 16.0, "x": 167.755381, "y": 36.666913}, "17": {"neighbours": [2, 4, 13, 20, 95, 112, 125], "node_range": 16.0, "x": 36.450091, "y": 50.634072}, "18": {"neighbours": [64, 68, 96, 124, 157, 186], "node_range": 16.0, "x": 134.05938, "y": 37.855264}, "19": {"neighbours": [50], "node_range": 16.0, "x": 79.210237, "y": 116.306777}, "20": {"neighbours": [4, 13, 17, 52, 75, 112, 127, 193], "node_range": 16.0, "x": 44.351584, "y": 47.871143}, "21": {"neighbours": [83, 197], "node_range": 16.0, "x": 25.873762, "y": 193.636713}, "22": {"neighbours": [61, 67, 80], "node_range": 16.0, "x": 62.827111, "y": 109.160652}, "23": {"neighbours": [145], "node_range": 16.0, "x": 187.66255, "y": 6.944585}, "24": {"neighbours": [29], "node_range": 16.0, "x": 69.468416, "y": 61.778796}, "25": {"neighbours": [172, 191], "node_range": 16.0, "x": 125.793561, "y": 116.818413}, "26": {"neighbours": [150], "node_range": 16.0, "x": 37.639506, "y": 111.494436}, "27": {"neighbours": [34, 155], "node_range": 16.0, "x": 17.262489, "y": 78.828054}, "28": {"neighbours": [44, 57, 65, 77], "node_range": 16.0, "x": 159.092067, "y": 174.269698}, "29": {"neighbours": [24, 62], "node_range": 16.0, "x": 64.697956, "y": 76.598386}, "30": {"neighbours": [35, 39, 104, 117, 120], "node_range": 16.0, "x": 174.078177, "y": 80.32272}, "31": {"neighbours": [60, 108, 185, 194], "node_range": 16.0, "x": 144.713873, "y": 83.038094}, "32": {"neighbours": [40, 70, 190], "node_range": 16.0, "x": 61.493095, "y": 177.699241}, "33": {"neighbours": [59, 140], "node_range": 16.0, "x": 161.565786, "y": 64.664205}, "34": {"neighbours": [27, 155], "node_range": 16.0, "x": 21.598248, "y": 75.406591}, "35": {"neighbours": [30, 39, 104, 117, 120], "node_range": 16.0, "x": 185.125692, "y": 79.984032}, "36": {"neighbours": [47, 53, 72, 191, 194], "node_range": 16.0, "x": 122.604363, "y": 100.241487}, "37": {"neighbours": [42, 133, 149, 192, 200], "node_range": 16.0, "x": 177.376806, "y": 127.928049}, "38": {"neighbours": [87, 114], "node_range": 16.0, "x": 145.041566, "y": 15.755595}, "39": {"neighbours": [30, 35, 102, 104, 117, 120], "node_range": 16.0, "x": 182.740101, "y": 84.897849}, "40": {"neighbours": [32, 70, 143], "node_range": 16.0, "x": 68.164813, "y": 186.30115}, "41": {"neighbours": [73, 90, 141, 161], "node_range": 16.0, "x": 137.871463, "y": 143.650338}, "42": {"neighbours": [12, 37, 135, 136, 149, 192, 200], "node_range": 16.0, "x": 187.425519, "y": 120.587025}, "43": {"neighbours": [2, 56, 79, 85, 142], "node_range": 16.0, "x": 18.249821, "y": 33.967782}, "44": {"neighbours": [28, 57, 65, 77, 131], "node_range": 16.0, "x": 150.507836, "y": 173.701701}, "45": {"neighbours": [46, 152], "node_range": 16.0, "x": 5.920103, "y": 114.817412}, "46": {"neighbours": [45, 152, 195], "node_range": 16.0, "x": 7.665008, "y": 127.820653}, "47": {"neighbours": [5, 36, 51, 72], "node_range": 16.0, "x": 113.157649, "y": 99.913508}, "48": {"neighbours": [153], "node_range": 16.0, "x": 193.489407, "y": 47.470429}, "49": {"neighbours": [197], "node_range": 16.0, "x": 42.660332, "y": 186.933131}, "50": {"neighbours": [19, 76], "node_range": 16.0, "x": 84.968227, "y": 117.112816}, "51": {"neighbours": [5, 7, 47, 72, 160], "node_range": 16.0, "x": 99.466213, "y": 103.032758}, "52": {"neighbours": [4, 13, 20, 75, 127, 193], "node_range": 16.0, "x": 52.497489, "y": 53.515871}, "53": {"neighbours": [6, 36, 58, 108, 185, 191, 194, 198], "node_range": 16.0, "x": 135.750031, "y": 103.815087}, "54": {"neighbours": [10, 14, 69, 92, 115], "node_range": 16.0, "x": 101.230081, "y": 52.946263}, "55": {"neighbours": [92, 115, 116], "node_range": 16.0, "x": 105.891994, "y": 32.060538}, "56": {"neighbours": [2, 43, 79, 85, 142, 189], "node_range": 16.0, "x": 23.531694, "y": 27.208895}, "57": {"neighbours": [28, 44, 77], "node_range": 16.0, "x": 161.17734, "y": 169.377665}, "58": {"neighbours": [6, 53, 185, 191, 194, 198], "node_range": 16.0, "x": 142.71323, "y": 109.339957}, "59": {"neighbours": [33], "node_range": 16.0, "x": 157.463254, "y": 62.709546}, "60": {"neighbours": [31, 108, 183, 194], "node_range": 16.0, "x": 138.307556, "y": 80.652903}, "61": {"neighbours": [22, 80, 148], "node_range": 16.0, "x": 62.035523, "y": 101.012069}, "62": {"neighbours": [29, 148, 187], "node_range": 16.0, "x": 56.253574, "y": 84.14724}, "63": {"neighbours": [163], "node_range": 16.0, "x": 168.643896, "y": 187.792923}, "64": {"neighbours": [18, 68, 122, 186], "node_range": 16.0, "x": 133.457011, "y": 50.288174}, "65": {"neighbours": [28, 44, 77, 131], "node_range": 16.0, "x": 148.442448, "y": 179.49641}, "66": {"neighbours": [14, 171], "node_range": 16.0, "x": 85.998438, "y": 72.39567}, "67": {"neighbours": [22, 150], "node_range": 16.0, "x": 57.376753, "y": 117.018701}, "68": {"neighbours": [18, 64, 122, 157, 186], "node_range": 16.0, "x": 139.685265, "y": 38.8513}, "69": {"neighbours": [14, 54, 166], "node_range": 16.0, "x": 111.451382, "y": 64.862404}, "70": {"neighbours": [32, 40, 143], "node_range": 16.0, "x": 67.589484, "y": 189.21906}, "71": {"neighbours": [3, 94, 109], "node_range": 16.0, "x": 76.361501, "y": 137.716413}, "72": {"neighbours": [5, 36, 47, 51, 111, 172], "node_range": 16.0, "x": 111.920614, "y": 108.759612}, "73": {"neighbours": [41, 139], "node_range": 16.0, "x": 130.533088, "y": 150.069169}, "74": {"neighbours": [132, 170], "node_range": 16.0, "x": 8.347717, "y": 161.923774}, "75": {"neighbours": [4, 20, 52, 127, 193], "node_range": 16.0, "x": 53.442198, "y": 46.809135}, "76": {"neighbours": [5, 50, 88, 103, 111], "node_range": 16.0, "x": 98.176644, "y": 121.177093}, "77": {"neighbours": [28, 44, 57, 65, 131], "node_range": 16.0, "x": 151.954761, "y": 179.452514}, "78": {"neighbours": [86, 106], "node_range": 16.0, "x": 2.162272, "y": 17.202764}, "79": {"neighbours": [43, 56, 85, 142], "node_range": 16.0, "x": 13.286765, "y": 30.943639}, "80": {"neighbours": [22, 61, 148], "node_range": 16.0, "x": 63.570006, "y": 100.0833}, "81": {"neighbours": [123], "node_range": 16.0, "x": 0.589306, "y": 199.530784}, "82": {"neighbours": [107, 180], "node_range": 16.0, "x": 40.223602, "y": 6.603834}, "83": {"neighbours": [21, 91, 197], "node_range": 16.0, "x": 21.230669, "y": 188.543091}, "84": {"neighbours": [119, 167], "node_range": 16.0, "x": 1.197672, "y": 92.550972}, "85": {"neighbours": [2, 43, 56, 79, 142, 189], "node_range": 16.0, "x": 24.66358, "y": 27.054424}, "86": {"neighbours": [78, 106], "node_range": 16.0, "x": 14.375068, "y": 9.861087}, "87": {"neighbours": [38, 99, 176], "node_range": 16.0, "x": 152.760673, "y": 20.083179}, "88": {"neighbours": [76, 103], "node_range": 16.0, "x": 96.016043, "y": 132.381236}, "89": {"neighbours": [3, 97, 109, 128, 175, 190], "node_range": 16.0, "x": 81.926925, "y": 154.504575}, "90": {"neighbours": [8, 41, 161], "node_range": 16.0, "x": 138.029452, "y": 134.298651}, "91": {"neighbours": [83, 170], "node_range": 16.0, "x": 24.872767, "y": 174.220064}, "92": {"neighbours": [10, 54, 55, 115], "node_range": 16.0, "x": 96.343782, "y": 38.003409}, "93": {"neighbours": [135], "node_range": 16.0, "x": 195.941453, "y": 138.827373}, "94": {"neighbours": [3, 71, 109], "node_range": 16.0, "x": 65.262162, "y": 144.421289}, "95": {"neighbours": [17, 112, 125], "node_range": 16.0, "x": 28.729729, "y": 52.78447}, "96": {"neighbours": [18, 124, 157], "node_range": 16.0, "x": 128.923359, "y": 23.87047}, "97": {"neighbours": [89, 109, 175, 190], "node_range": 16.0, "x": 73.40572, "y": 161.726168}, "98": {"neighbours": [145, 156], "node_range": 16.0, "x": 196.3019, "y": 22.296443}, "99": {"neighbours": [87, 154, 176], "node_range": 16.0, "x": 162.123775, "y": 9.972082}, "100": {"neighbours": [146, 168], "node_range": 16.0, "x": 73.830311, "y": 21.470177}, "101": {"neighbours": [138], "node_range": 16.0, "x": 73.745572, "y": 3.054109}, "102": {"neighbours": [12, 39, 136, 159, 169, 199], "node_range": 16.0, "x": 189.35968, "y": 99.293246}, "103": {"neighbours": [76, 88, 111], "node_range": 16.0, "x": 98.588716, "y": 129.281098}, "104": {"neighbours": [30, 35, 39, 117, 120], "node_range": 16.0, "x": 182.817494, "y": 77.442871}, "105": {"neighbours": [177], "node_range": 16.0, "x": 177.597915, "y": 173.147684}, "106": {"neighbours": [78, 86], "node_range": 16.0, "x": 10.440341, "y": 8.607551}, "107": {"neighbours": [82, 138, 180], "node_range": 16.0, "x": 47.201381, "y": 4.681739}, "108": {"neighbours": [6, 31, 53, 60, 185, 194], "node_range": 16.0, "x": 139.861681, "y": 90.279778}, "109": {"neighbours": [3, 71, 89, 94, 97, 175], "node_range": 16.0, "x": 72.494098, "y": 151.01724}, "110": {"neighbours": [6, 174], "node_range": 16.0, "x": 165.454259, "y": 100.574344}, "111": {"neighbours": [5, 72, 76, 103, 172], "node_range": 16.0, "x": 108.040138, "y": 116.888254}, "112": {"neighbours": [2, 17, 20, 95, 125, 142], "node_range": 16.0, "x": 31.479011, "y": 47.789888}, "113": {"neighbours": [141, 177, 184], "node_range": 16.0, "x": 165.603043, "y": 152.056283}, "114": {"neighbours": [38], "node_range": 16.0, "x": 140.134172, "y": 3.710735}, "115": {"neighbours": [54, 55, 92, 116, 129], "node_range": 16.0, "x": 110.38879, "y": 40.474768}, "116": {"neighbours": [55, 115, 124, 129, 157], "node_range": 16.0, "x": 116.702184, "y": 41.125338}, "117": {"neighbours": [30, 35, 39, 104, 120], "node_range": 16.0, "x": 176.047804, "y": 79.348195}, "118": {"neighbours": [178], "node_range": 16.0, "x": 32.709023, "y": 160.200004}, "119": {"neighbours": [84, 167], "node_range": 16.0, "x": 0.562691, "y": 78.386923}, "120": {"neighbours": [30, 35, 39, 104, 117], "node_range": 16.0, "x": 182.790309, "y": 79.01857}, "121": {"neighbours": [137, 151, 173, 178], "node_range": 16.0, "x": 32.829041, "y": 142.723164}, "122": {"neighbours": [64, 68, 186], "node_range": 16.0, "x": 144.964241, "y": 49.625831}, "123": {"neighbours": [81], "node_range": 16.0, "x": 8.594066, "y": 199.298152}, "124": {"neighbours": [18, 96, 116, 157], "node_range": 16.0, "x": 121.986066, "y": 27.934337}, "125": {"neighbours": [17, 95, 112], "node_range": 16.0, "x": 23.90239, "y": 53.278868}, "126": {"neighbours": [139, 158], "node_range": 16.0, "x": 120.54332, "y": 166.27948}, "127": {"neighbours": [4, 20, 52, 75, 193], "node_range": 16.0, "x": 56.547201, "y": 44.168076}, "128": {"neighbours": [89, 175], "node_range": 16.0, "x": 89.168917, "y": 164.98841}, "129": {"neighbours": [115, 116], "node_range": 16.0, "x": 117.560516, "y": 47.481517}, "130": {"neighbours": [152], "node_range": 16.0, "x": 22.51959, "y": 119.269341}, "131": {"neighbours": [44, 65, 77, 196], "node_range": 16.0, "x": 141.935631, "y": 179.25488}, "132": {"neighbours": [74, 170, 178, 195], "node_range": 16.0, "x": 18.625427, "y": 151.474654}, "133": {"neighbours": [37, 149, 192, 200], "node_range": 16.0, "x": 175.376009, "y": 131.509403}, "134": {"neighbours": [151, 173], "node_range": 16.0, "x": 46.225821, "y": 129.237333}, "135": {"neighbours": [42, 93], "node_range": 16.0, "x": 196.009872, "y": 132.397275}, "136": {"neighbours": [12, 42, 102, 149, 192, 200], "node_range": 16.0, "x": 183.317849, "y": 113.040361}, "137": {"neighbours": [121, 151, 178, 182], "node_range": 16.0, "x": 42.528806, "y": 145.916347}, "138": {"neighbours": [101, 107], "node_range": 16.0, "x": 58.227039, "y": 6.458565}, "139": {"neighbours": [73, 126, 181], "node_range": 16.0, "x": 122.097982, "y": 150.739343}, "140": {"neighbours": [9, 33], "node_range": 16.0, "x": 173.29971, "y": 56.255461}, "141": {"neighbours": [41, 113, 161], "node_range": 16.0, "x": 152.462333, "y": 144.832005}, "142": {"neighbours": [2, 43, 56, 79, 85, 112], "node_range": 16.0, "x": 22.916143, "y": 35.87547}, "143": {"neighbours": [40, 70, 190], "node_range": 16.0, "x": 77.712365, "y": 181.349816}, "144": {"neighbours": [147], "node_range": 16.0, "x": 196.618212, "y": 157.491486}, "145": {"neighbours": [23, 98, 156], "node_range": 16.0, "x": 183.785629, "y": 15.91489}, "146": {"neighbours": [100, 168], "node_range": 16.0, "x": 72.230142, "y": 25.436415}, "147": {"neighbours": [144], "node_range": 16.0, "x": 195.975697, "y": 165.81239}, "148": {"neighbours": [61, 62, 80, 187], "node_range": 16.0, "x": 52.513182, "y": 90.39236}, "149": {"neighbours": [12, 37, 42, 133, 136, 192, 200], "node_range": 16.0, "x": 176.476305, "y": 118.119937}, "150": {"neighbours": [26, 67], "node_range": 16.0, "x": 46.20436, "y": 112.447184}, "151": {"neighbours": [121, 134, 137, 173], "node_range": 16.0, "x": 43.222727, "y": 136.10955}, "152": {"neighbours": [45, 46, 130], "node_range": 16.0, "x": 17.198711, "y": 119.75338}, "153": {"neighbours": [48], "node_range": 16.0, "x": 191.733311, "y": 42.82751}, "154": {"neighbours": [99], "node_range": 16.0, "x": 160.10143, "y": 1.263154}, "155": {"neighbours": [27, 34], "node_range": 16.0, "x": 24.434989, "y": 71.074334}, "156": {"neighbours": [98, 145], "node_range": 16.0, "x": 182.405836, "y": 29.199274}, "157": {"neighbours": [18, 68, 96, 116, 124], "node_range": 16.0, "x": 126.21039, "y": 30.406239}, "158": {"neighbours": [126, 162], "node_range": 16.0, "x": 114.179474, "y": 164.686578}, "159": {"neighbours": [102, 169, 199], "node_range": 16.0, "x": 199.23572, "y": 95.641482}, "160": {"neighbours": [7, 51], "node_range": 16.0, "x": 92.993669, "y": 98.055336}, "161": {"neighbours": [8, 41, 90, 141], "node_range": 16.0, "x": 148.834436, "y": 136.175836}, "162": {"neighbours": [158], "node_range": 16.0, "x": 109.236673, "y": 179.804978}, "163": {"neighbours": [63], "node_range": 16.0, "x": 178.724477, "y": 193.827347}, "164": {"neighbours": [1], "node_range": 16.0, "x": 91.952779, "y": 190.827685}, "165": {"neighbours": [4, 13, 187], "node_range": 16.0, "x": 43.469422, "y": 71.071465}, "166": {"neighbours": [7, 69], "node_range": 16.0, "x": 106.548707, "y": 78.779124}, "167": {"neighbours": [84, 119], "node_range": 16.0, "x": 0.603364, "y": 89.610664}, "168": {"neighbours": [100, 146], "node_range": 16.0, "x": 71.629767, "y": 27.361286}, "169": {"neighbours": [102, 159, 199], "node_range": 16.0, "x": 199.559112, "y": 86.99508}, "170": {"neighbours": [74, 91, 132], "node_range": 16.0, "x": 16.532481, "y": 166.285432}, "171": {"neighbours": [14, 66], "node_range": 16.0, "x": 83.5814, "y": 69.714114}, "172": {"neighbours": [5, 25, 72, 111], "node_range": 16.0, "x": 119.987162, "y": 116.397772}, "173": {"neighbours": [121, 134, 151], "node_range": 16.0, "x": 38.254059, "y": 128.688203}, "174": {"neighbours": [6, 110, 185], "node_range": 16.0, "x": 158.5874, "y": 91.449239}, "175": {"neighbours": [3, 89, 97, 109, 128], "node_range": 16.0, "x": 84.442091, "y": 154.968621}, "176": {"neighbours": [16, 87, 99], "node_range": 16.0, "x": 163.849145, "y": 21.829594}, "177": {"neighbours": [105, 113, 184], "node_range": 16.0, "x": 178.297503, "y": 161.638549}, "178": {"neighbours": [118, 121, 132, 137], "node_range": 16.0, "x": 26.977122, "y": 145.363541}, "179": {"neighbours": [182], "node_range": 16.0, "x": 53.074358, "y": 158.998579}, "180": {"neighbours": [82, 107, 189], "node_range": 16.0, "x": 44.078166, "y": 17.046073}, "181": {"neighbours": [139], "node_range": 16.0, "x": 108.017261, "y": 148.972728}, "182": {"neighbours": [137, 179], "node_range": 16.0, "x": 48.839311, "y": 152.128703}, "183": {"neighbours": [60], "node_range": 16.0, "x": 128.60889, "y": 71.177421}, "184": {"neighbours": [113, 177], "node_range": 16.0, "x": 177.460668, "y": 154.165058}, "185": {"neighbours": [6, 31, 53, 58, 108, 174, 191, 194, 198], "node_range": 16.0, "x": 145.208698, "y": 97.013388}, "186": {"neighbours": [18, 64, 68, 122], "node_range": 16.0, "x": 141.106488, "y": 44.251215}, "187": {"neighbours": [62, 148, 165], "node_range": 16.0, "x": 45.566321, "y": 86.910512}, "188": {"neighbours": [11, 15, 196], "node_range": 16.0, "x": 128.558733, "y": 191.574519}, "189": {"neighbours": [2, 56, 85, 180], "node_range": 16.0, "x": 31.70443, "y": 20.627695}, "190": {"neighbours": [32, 89, 97, 143], "node_range": 16.0, "x": 72.184572, "y": 167.182526}, "191": {"neighbours": [25, 36, 53, 58, 185, 194, 198], "node_range": 16.0, "x": 132.653499, "y": 105.632032}, "192": {"neighbours": [12, 37, 42, 133, 136, 149, 200], "node_range": 16.0, "x": 173.978313, "y": 123.575136}, "193": {"neighbours": [20, 52, 75, 127], "node_range": 16.0, "x": 55.22827, "y": 39.964851}, "194": {"neighbours": [6, 31, 36, 53, 58, 60, 108, 185, 191, 198], "node_range": 16.0, "x": 135.859552, "y": 96.344017}, "195": {"neighbours": [46, 132], "node_range": 16.0, "x": 10.527637, "y": 138.127548}, "196": {"neighbours": [131, 188], "node_range": 16.0, "x": 129.028448, "y": 180.872222}, "197": {"neighbours": [21, 49, 83], "node_range": 16.0, "x": 32.731, "y": 193.335968}, "198": {"neighbours": [6, 53, 58, 185, 191, 194], "node_range": 16.0, "x": 146.180107, "y": 106.977759}, "199": {"neighbours": [102, 159, 169], "node_range": 16.0, "x": 199.159451, "y": 91.541526}, "200": {"neighbours": [12, 37, 42, 133, 136, 149, 192], "node_range": 16.0, "x": 172.521268, "y": 116.058272}}